<?xml version="1.0" encoding="utf-8">
<odoo>
    <data>
        <template id="report_remito">
            <t t-call="web.html_container">
                <t t-foreach="docs" t-as="o">
                    <t t-call="web.basic_layout">
                        <div class="page">
                            <h2>Report title</h2>
                            <p>This object's name is <spam t-field="o.name"/></p>
                        </div>
                    </t>
                </t>
            </t>
        </template>
    </data>
</odoo>